{"circuit": {"n0004.sapling.stanford.edu": {"-l 10 -p 2 -npp 2500 -wpp 10000 -ll:cpu 2": [{"time_seconds": "3.181", "host": "n0004.sapling.stanford.edu", "date": "2017-02-10 07:35:54.853037", "commit": "796aa48d9cfea100e330631c53cd6c6aed00e847", "benchmark": "circuit", "argv": "-l 10 -p 2 -npp 2500 -wpp 10000 -ll:cpu 2"}, {"time_seconds": "3.168", "host": "n0004.sapling.stanford.edu", "date": "2017-02-10 07:07:18.813669", "commit": "3344a277cf718afc5bf95ffd2fc8f6063125c5d6", "benchmark": "circuit", "argv": "-l 10 -p 2 -npp 2500 -wpp 10000 -ll:cpu 2"}], "-l 10 -p 100 -npp 2 -wpp 4 -ll:cpu 2": [{"time_seconds": "3.242", "host": "n0004.sapling.stanford.edu", "date": "2017-02-10 07:07:23.797746", "commit": "3344a277cf718afc5bf95ffd2fc8f6063125c5d6", "benchmark": "circuit", "argv": "-l 10 -p 100 -npp 2 -wpp 4 -ll:cpu 2"}, {"time_seconds": "2.955", "host": "n0004.sapling.stanford.edu", "date": "2017-02-10 07:35:59.368868", "commit": "796aa48d9cfea100e330631c53cd6c6aed00e847", "benchmark": "circuit", "argv": "-l 10 -p 100 -npp 2 -wpp 4 -ll:cpu 2"}]}}}